README.rst
setup.py
rcomp/__init__.py
rcomp/_version.py
rcomp/cli.py
rcomp.egg-info/PKG-INFO
rcomp.egg-info/SOURCES.txt
rcomp.egg-info/dependency_links.txt
rcomp.egg-info/entry_points.txt
rcomp.egg-info/requires.txt
rcomp.egg-info/top_level.txt