Metadata-Version: 1.1
Name: rcomp
Version: 0.0.0
Summary: client of the rcomp server
Home-page: https://github.com/slivingston/rcomp
Author: Scott C. Livingston
Author-email: slivingston@cds.caltech.edu
License: BSD
Platform: UNKNOWN
Classifier: Programming Language :: Python :: 2
Classifier: Programming Language :: Python :: 2.7
Classifier: Programming Language :: Python :: 3
Classifier: Programming Language :: Python :: 3.4
Classifier: Programming Language :: Python :: 3.5
